MANIFEST.in
README.rst
setup.py
digitaldiocese/__init__.py
digitaldiocese/acny/__init__.py
digitaldiocese/acny/admin.py
digitaldiocese/acny/apps.py
digitaldiocese/acny/choices.py
digitaldiocese/acny/fields.py
digitaldiocese/acny/forms.py
digitaldiocese/acny/layouts.py
digitaldiocese/acny/models.py
digitaldiocese/acny/search_indexes.py
digitaldiocese/acny/tests.py
digitaldiocese/acny/urls.py
digitaldiocese/acny/utils.py
digitaldiocese/acny/views.py
digitaldiocese/acny/management/__init__.py
digitaldiocese/acny/management/commands/__init__.py
digitaldiocese/acny/management/commands/geocode_churches.py
digitaldiocese/acny/migrations/0001_initial.py
digitaldiocese/acny/migrations/0002_county_length.py
digitaldiocese/acny/migrations/0003_rename_acny_id.py
digitaldiocese/acny/migrations/0004_legacy_acny_id_null.py
digitaldiocese/acny/migrations/0005_people_services_blocks.py
digitaldiocese/acny/migrations/0006_personblock_content.py
digitaldiocese/acny/migrations/0007_role_church_null.py
digitaldiocese/acny/migrations/0008_auto_20161027_0924.py
digitaldiocese/acny/migrations/0009_place_types.py
digitaldiocese/acny/migrations/0010_people_worthers.py
digitaldiocese/acny/migrations/0011_benefice_roles.py
digitaldiocese/acny/migrations/0012_roleblock.py
digitaldiocese/acny/migrations/0013_rename_church_block.py
digitaldiocese/acny/migrations/0014_churchservice_add_date_recurring.py
digitaldiocese/acny/migrations/0015_title_max_length.py
digitaldiocese/acny/migrations/0016_charfield_max_lengths.py
digitaldiocese/acny/migrations/__init__.py
digitaldiocese/acny/templatetags/__init__.py
digitaldiocese/acny/templatetags/acny_tags.py
digitaldiocese/carousel/__init__.py
digitaldiocese/carousel/admin.py
digitaldiocese/carousel/apps.py
digitaldiocese/carousel/blocks.py
digitaldiocese/carousel/models.py
digitaldiocese/carousel/migrations/0001_initial.py
digitaldiocese/carousel/migrations/__init__.py
digitaldiocese/core/__init__.py
digitaldiocese/core/management/__init__.py
django_digitaldiocese.egg-info/PKG-INFO
django_digitaldiocese.egg-info/SOURCES.txt
django_digitaldiocese.egg-info/dependency_links.txt
django_digitaldiocese.egg-info/requires.txt
django_digitaldiocese.egg-info/top_level.txt