Metadata-Version: 1.0
Name: django-digitaldiocese
Version: 2.1.9
Summary: Handbook
Home-page: https://github.com/developersociety/django-digitaldiocese
Author: The Developer Society
Author-email: studio@dev.ngo
License: BSD
Platform: UNKNOWN
